{
    "required": true,
    "minVersion": "0.8",
    "compatibilityLevel": "JAVA_8",
    "package": "dev.onyxstudios.cca.mixin.item",
    "plugin": "dev.onyxstudios.cca.mixin.CardinalItemMixinPlugin",
    "mixins": [
        "common.MixinBookCloningRecipe",
        "common.MixinCauldronBlock",
        "common.MixinItem",
        "common.MixinItemEntity",
        "common.MixinItemStack",
        "common.MixinOnAStickItem",
        "common.MixinPacketByteBuf",
        "common.MixinPlayerInventory",
        "common.MixinShulkerBoxColoringRecipe",
        "common.MixinSmithingRecipe",
        "common.MixinWritePacketByteBuf",
        "common.MixinWritePacketByteBufOF"
    ],
    "injectors": {
        "defaultRequire": 1
    }
}
